ymodem/CRC.py
ymodem/Platform.py
ymodem/Protocol.py
ymodem/Socket.py
ymodem/Version.py
ymodem/__init__.py
ymodem/__main__.py
ymodem-1.5.1.dist-info/LICENSE
ymodem-1.5.1.dist-info/METADATA
ymodem-1.5.1.dist-info/WHEEL
ymodem-1.5.1.dist-info/entry_points.txt
ymodem-1.5.1.dist-info/top_level.txt
ymodem-1.5.1.dist-info/RECORD
