Metadata-Version: 2.1
Name: ymodem
Version: 1.5.1
Summary: Ymodem Python3 implementation
Project-URL: Homepage, https://github.com/alexwoo1900/ymodem
Project-URL: Bug Reports, https://github.com/alexwoo1900/ymodem/issues
Project-URL: Source, https://github.com/alexwoo1900/ymodem
Keywords: pyserial,serial,xmodem,ymodem,python,python3
Classifier: Intended Audience :: Developers
Classifier: Natural Language :: English
Classifier: Programming Language :: Python
Classifier: Topic :: Software Development :: Libraries :: Python Modules
Classifier: Programming Language :: Python :: 3
Classifier: Programming Language :: Python :: 3 :: Only
Classifier: Programming Language :: Python :: 3.7
Classifier: Programming Language :: Python :: 3.8
Classifier: Programming Language :: Python :: 3.9
Classifier: Programming Language :: Python :: 3.10
Classifier: Programming Language :: Python :: 3.11
Classifier: Programming Language :: Python :: 3.12
Classifier: Operating System :: OS Independent
Classifier: Programming Language :: Python :: Implementation :: CPython
Requires-Python: >=3.7
License-File: LICENSE
Requires-Dist: ordered-set >=4.1.0
Requires-Dist: pyserial
